miniflux_tui/__init__.py
miniflux_tui/__main__.py
miniflux_tui/change_tracker.py
miniflux_tui/config.py
miniflux_tui/constants.py
miniflux_tui/docs_cache.py
miniflux_tui/docs_fetcher.py
miniflux_tui/draft_manager.py
miniflux_tui/form_persistence_manager.py
miniflux_tui/main.py
miniflux_tui/performance.py
miniflux_tui/recovery_manager.py
miniflux_tui/security.py
miniflux_tui/themes.py
miniflux_tui/utils.py
miniflux_tui/api/__init__.py
miniflux_tui/api/client.py
miniflux_tui/api/models.py
miniflux_tui/scraping/__init__.py
miniflux_tui/scraping/analyzer.py
miniflux_tui/scraping/fetcher.py
miniflux_tui/ui/__init__.py
miniflux_tui/ui/app.py
miniflux_tui/ui/app_protocol.py
miniflux_tui/ui/base_screen.py
miniflux_tui/ui/protocols.py
miniflux_tui/ui/screens/__init__.py
miniflux_tui/ui/screens/category_management.py
miniflux_tui/ui/screens/confirm_dialog.py
miniflux_tui/ui/screens/entry_history.py
miniflux_tui/ui/screens/entry_list.py
miniflux_tui/ui/screens/entry_reader.py
miniflux_tui/ui/screens/feed_management.py
miniflux_tui/ui/screens/feed_settings.py
miniflux_tui/ui/screens/help.py
miniflux_tui/ui/screens/input_dialog.py
miniflux_tui/ui/screens/loading.py
miniflux_tui/ui/screens/rules_helper.py
miniflux_tui/ui/screens/scraping_helper.py
miniflux_tui/ui/screens/settings_edit_dialog.py
miniflux_tui/ui/screens/settings_management.py
miniflux_tui/ui/screens/status.py
miniflux_tui/ui/widgets/__init__.py
miniflux_tui/ui/widgets/safe_widgets.py
miniflux_tui_py-0.7.4.dist-info/METADATA
miniflux_tui_py-0.7.4.dist-info/WHEEL
miniflux_tui_py-0.7.4.dist-info/entry_points.txt
miniflux_tui_py-0.7.4.dist-info/licenses/AUTHORS.md
miniflux_tui_py-0.7.4.dist-info/licenses/LICENSE
miniflux_tui_py-0.7.4.dist-info/RECORD
