Metadata-Version: 2.4
Name: miniflux-tui-py
Version: 0.7.4
Summary: A Python TUI client for Miniflux RSS reader with feed sorting capabilities
Project-URL: Homepage, https://github.com/reuteras/miniflux-tui-py
Project-URL: Documentation, https://reuteras.github.io/miniflux-tui-py/
Project-URL: Repository, https://github.com/reuteras/miniflux-tui-py
Project-URL: Issues, https://github.com/reuteras/miniflux-tui-py/issues
Project-URL: Bug-tracker, https://github.com/reuteras/miniflux-tui-py/issues
Author-email: Peter Reuterås <peter@reuteras.net>
License: MIT
License-File: AUTHORS.md
License-File: LICENSE
Keywords: feed-reader,miniflux,rss,terminal,tui
Classifier: Development Status :: 5 - Production/Stable
Classifier: Environment :: Console
Classifier: Intended Audience :: End Users/Desktop
Classifier: License :: OSI Approved :: MIT License
Classifier: Natural Language :: English
Classifier: Operating System :: OS Independent
Classifier: Programming Language :: Python :: 3
Classifier: Programming Language :: Python :: 3.11
Classifier: Programming Language :: Python :: 3.12
Classifier: Programming Language :: Python :: 3.13
Classifier: Programming Language :: Python :: 3.14
Classifier: Programming Language :: Python :: 3.15
Classifier: Topic :: Internet
Classifier: Topic :: Internet :: WWW/HTTP
Classifier: Topic :: Internet :: WWW/HTTP :: Dynamic Content
Classifier: Topic :: Office/Business :: News/Diary
Classifier: Topic :: Utilities
Classifier: Typing :: Typed
Requires-Python: >=3.11
Requires-Dist: beautifulsoup4>=4.14.2
Requires-Dist: bleach>=6.3.0
Requires-Dist: html2text>=2025.4.15
Requires-Dist: html5lib>=1.1
Requires-Dist: httpx>=0.28.1
Requires-Dist: miniflux>=1.1.4
Requires-Dist: textual>=6.4.0
Requires-Dist: tomli>=2.0.1; python_version < '3.11'
Provides-Extra: binary
Requires-Dist: pyinstaller>=6.10.0; extra == 'binary'
Provides-Extra: dev
Requires-Dist: bandit[toml]>=1.7.5; extra == 'dev'
Requires-Dist: pylint>=4.0.2; extra == 'dev'
Requires-Dist: pyright>=1.1.0; extra == 'dev'
Requires-Dist: pytest-asyncio>=0.23.0; extra == 'dev'
Requires-Dist: pytest-benchmark>=4.0.0; extra == 'dev'
Requires-Dist: pytest-cov>=4.0.0; extra == 'dev'
Requires-Dist: pytest>=8.0.0; extra == 'dev'
Requires-Dist: ruff>=0.6.0; extra == 'dev'
Provides-Extra: docs
Requires-Dist: mkdocs-material>=9.6.22; extra == 'docs'
Requires-Dist: mkdocs>=1.6.1; extra == 'docs'
Requires-Dist: mkdocstrings[python]>=0.30.1; extra == 'docs'
Provides-Extra: fuzz
Requires-Dist: atheris>=2.3.0; extra == 'fuzz'
